dev_pipeline_configure-0.4.0.dist-info/DESCRIPTION.rst
dev_pipeline_configure-0.4.0.dist-info/METADATA
dev_pipeline_configure-0.4.0.dist-info/RECORD
dev_pipeline_configure-0.4.0.dist-info/WHEEL
dev_pipeline_configure-0.4.0.dist-info/entry_points.txt
dev_pipeline_configure-0.4.0.dist-info/metadata.json
dev_pipeline_configure-0.4.0.dist-info/top_level.txt
devpipeline_configure/__init__.py
devpipeline_configure/cache.py
devpipeline_configure/config.py
devpipeline_configure/configure.py
devpipeline_configure/local.py
devpipeline_configure/modifiers.py
devpipeline_configure/overrides.py
devpipeline_configure/packages.py
devpipeline_configure/parser.py
devpipeline_configure/profiles.py
devpipeline_configure/version.py
