Metadata-Version: 2.0
Name: dev-pipeline-configure
Version: 0.4.0
Summary: configure command for dev-pipeline
Home-page: https://github.com/dev-pipeline/dev-pipeline-configure
Author: Stephen Newell
Author-email: UNKNOWN
License: BSD-2
Platform: UNKNOWN
Classifier: Development Status :: 2 - Pre-Alpha
Classifier: Environment :: Plugins
Classifier: Intended Audience :: Developers
Classifier: License :: OSI Approved :: BSD License
Classifier: Topic :: Software Development
Classifier: Topic :: Utilities
Requires-Dist: dev-pipeline-core (>=0.4.0)
